grokcore.traverser-4.1-py3.12-nspkg.pth
grokcore/traverser/__init__.py
grokcore/traverser/components.py
grokcore/traverser/configure.zcml
grokcore/traverser/directive.py
grokcore/traverser/ftesting.zcml
grokcore/traverser/interfaces.py
grokcore/traverser/meta.py
grokcore/traverser/meta.zcml
grokcore/traverser/testing.py
grokcore/traverser/util.py
grokcore/traverser/tests/__init__.py
grokcore/traverser/tests/test_functional.py
grokcore/traverser/tests/functional/__init__.py
grokcore/traverser/tests/functional/traversal/__init__.py
grokcore/traverser/tests/functional/traversal/containertraverse.py
grokcore/traverser/tests/functional/traversal/containertraverser.py
grokcore/traverser/tests/functional/traversal/items_before_views.py
grokcore/traverser/tests/functional/traversal/modeltraverse.py
grokcore/traverser/tests/functional/traversal/traversableattr.py
grokcore/traverser/tests/functional/traversal/traverser.py
grokcore/traverser/tests/functional/traversal/traverser_sets_parent.py
grokcore/traverser/tests/functional/traversal/traverser_with_layer.py
grokcore_traverser-4.1.dist-info/licenses/LICENSE.txt
grokcore_traverser-4.1.dist-info/METADATA
grokcore_traverser-4.1.dist-info/WHEEL
grokcore_traverser-4.1.dist-info/namespace_packages.txt
grokcore_traverser-4.1.dist-info/top_level.txt
grokcore_traverser-4.1.dist-info/RECORD
