Metadata-Version: 2.4
Name: grokcore.traverser
Version: 4.1
Summary: Traverser for the Grok Framework
Home-page: https://github.com/zopefoundation/grokcore.traverser
Author: Grok Team
Author-email: zope-dev@zope.dev
License: ZPL
Classifier: Environment :: Web Environment
Classifier: Intended Audience :: Developers
Classifier: License :: OSI Approved :: Zope Public License
Classifier: Programming Language :: Python
Classifier: Programming Language :: Python :: 3
Classifier: Programming Language :: Python :: 3.9
Classifier: Programming Language :: Python :: 3.10
Classifier: Programming Language :: Python :: 3.11
Classifier: Programming Language :: Python :: 3.12
Classifier: Programming Language :: Python :: 3.13
Classifier: Programming Language :: Python :: Implementation
Classifier: Programming Language :: Python :: Implementation :: CPython
Classifier: Programming Language :: Python :: Implementation :: PyPy
Classifier: Framework :: Zope :: 3
Requires-Python: >=3.9
License-File: LICENSE.txt
Requires-Dist: grokcore.component>=2.5
Requires-Dist: grokcore.security
Requires-Dist: grokcore.view
Requires-Dist: martian
Requires-Dist: setuptools
Requires-Dist: zope.component
Requires-Dist: zope.interface
Requires-Dist: zope.publisher
Provides-Extra: test
Requires-Dist: grokcore.content; extra == "test"
Requires-Dist: grokcore.view[test]; extra == "test"
Requires-Dist: zope.app.appsetup; extra == "test"
Requires-Dist: zope.app.wsgi; extra == "test"
Requires-Dist: zope.login; extra == "test"
Requires-Dist: zope.principalregistry; extra == "test"
Requires-Dist: zope.securitypolicy; extra == "test"
Requires-Dist: zope.testbrowser; extra == "test"
Requires-Dist: zope.testing; extra == "test"
Dynamic: author
Dynamic: author-email
Dynamic: classifier
Dynamic: description
Dynamic: home-page
Dynamic: license
Dynamic: license-file
Dynamic: provides-extra
Dynamic: requires-dist
Dynamic: requires-python
Dynamic: summary
